pokerrl_env/__init__.py
pokerrl_env/cardlib.py
pokerrl_env/config.py
pokerrl_env/datatypes.py
pokerrl_env/game.py
pokerrl_env/play.py
pokerrl_env/test_pots.py
pokerrl_env/test_transition.py
pokerrl_env/test_utils.py
pokerrl_env/test_view.py
pokerrl_env/transition.py
pokerrl_env/utils.py
pokerrl_env/view.py
pokerrl_env-0.1.4.dist-info/METADATA
pokerrl_env-0.1.4.dist-info/WHEEL
pokerrl_env-0.1.4.dist-info/RECORD
