Metadata-Version: 2.1
Name: pokerrl_env
Version: 0.1.4
Summary: A poker environment for reinforcement learning
License: MIT
Author: Morgan Griffiths
Author-email: rareducks101@yahoo.com
Requires-Python: ==3.11.5
Classifier: License :: OSI Approved :: MIT License
Classifier: Programming Language :: Python :: 3
Requires-Dist: numpy (==1.24.2)
Requires-Dist: pytest (==6.2.4)
Requires-Dist: setuptools-rust (==1.5.2)
